bearface/__init__.py
bearface/import_utils.py
bearface/pytorch.py
bearface/registry.py
bearface/resolvers.py
bearface-0.0.1.dist-info/METADATA
bearface-0.0.1.dist-info/LICENSE
bearface-0.0.1.dist-info/WHEEL
bearface-0.0.1.dist-info/RECORD
