Metadata-Version: 2.1
Name: bearface
Version: 0.0.1
Summary: A library of custom OmegaConf resolvers
Home-page: https://github.com/durandtibo/bearface
License: BSD-3-Clause
Keywords: omegaconf,resolver
Author: Thibaut Durand
Author-email: durand.tibo+gh@gmail.com
Requires-Python: >=3.9,<4.0
Classifier: Development Status :: 3 - Alpha
Classifier: Intended Audience :: Developers
Classifier: Intended Audience :: Information Technology
Classifier: Intended Audience :: Science/Research
Classifier: License :: OSI Approved :: BSD License
Classifier: Operating System :: POSIX :: Linux
Classifier: Programming Language :: Python :: 3
Classifier: Programming Language :: Python :: 3.9
Classifier: Programming Language :: Python :: 3.10
Classifier: Programming Language :: Python :: 3.11
Classifier: Programming Language :: Python :: 3.10
Classifier: Programming Language :: Python :: 3.11
Classifier: Programming Language :: Python :: 3.9
Classifier: Topic :: Scientific/Engineering
Classifier: Topic :: Software Development :: Libraries
Provides-Extra: all
Requires-Dist: omegaconf (>=2.1,<3.0)
Requires-Dist: torch (>=1.10,<2.0) ; (python_version < "3.11") and (extra == "all")
Project-URL: Repository, https://github.com/durandtibo/bearface
